{
    "bibitems": [
    ],
    "bibtexfiles": [
        "/Users/danielm/Documents/literatura.bib#literatura.bib"
    ],
    "childdocs": [
    ],
    "filename": "/Users/danielm/Documents/untitled.tex",
    "labels": [
        "fig:sino",
        "fig:ctf_phase",
        "fig:nerf_representation",
        "fig:fbp",
        "fig:formation-holo",
        "eq:loss_function",
        "fig:onix_training",
        "fig:singular_val",
        "fig:pix_nerf2",
        "fig:dataset_ffc",
        "fig:bragg",
        "eq:transmission_function",
        "fig:comparasion",
        "fig:tomoscopy_scheme",
        "fig:phase_retrieval",
        "fig:sirt",
        "fig:flat_approx",
        "fig:ffc2",
        "eq:volume_rendering",
        "fig:onix",
        "eq:SVD",
        "Flat-field correction",
        "eq:ART",
        "fig:onix_dson33_slices",
        "fig:nerf_intro",
        "fig:backproj",
        "sec:tomo_rec",
        "fig:inline-holo",
        "fig:onix_dson32_proj",
        "fig:onix_dson32_slices",
        "eq:Radiance fields",
        "fig:singular_modes",
        "fig:pix_nerf"
    ],
    "modified": "Mon Apr 22 20:18:54 2024",
    "packages": [
        "#array",
        "T1#fontenc",
        "#graphicx",
        "#float",
        "bbgreekl#mathbbol",
        "#amssymb",
        "#blindtext",
        "#subcaption",
        "#multicol",
        "#palatino",
        "#caption",
        "#chngcntr",
        "#fancyhdr",
        "#amsmath",
        "#siunitx",
        "#pdfpages",
        "english,slovak#babel",
        "a4paper,top=2cm,bottom=2cm,left=3cm,right=3cm,marginparwidth=1.75cm#geometry",
        "#array",
        "#comment",
        "#tikz",
        "#cleveref",
        "#caption",
        "#graphicx",
        "skip=0.333\\baselineskip#caption",
        "#setspace",
        "colorlinks=true, allcolors=blue#hyperref",
        "colorlinks=true, allcolors=blue#nameref",
        "utf8#inputenc",
        "#animate",
        "#colortbl",
        "#amsfonts",
        "#braket",
        "#stackengine",
        "#latex-document",
        "#tex",
        "#amsfonts"
    ],
    "refs": [
        "eq:Radiance fields",
        "fig:comparasion",
        "Flat-field correction",
        "Flat-field correction",
        "fig:onix_dson32_proj",
        "fig:onix_dson33_slices",
        "fig:onix_dson32_slices",
        "fig:inline-holo",
        "fig:onix_dson32_proj",
        "sec:tomo_rec",
        "sec:tomo_rec",
        "fig:fbp"
    ],
    "toc": [
        "-1#titulna_strana#84",
        "-1#cestne_prehlasenie#86",
        "-1#podakovanie#87",
        "2#Acronyms#121",
        "2#Introduction#160",
        "2#Theoretical Background#183",
        "3#MHz Tomoscopy and Time-resolved tomography#184",
        "3#X-ray phase-contrast imaging#196",
        "4#Image formation on detector#212",
        "3#Flat-field correction#225",
        "4#Flat-field correction methods#228",
        "3#Bragg magnifier and Phase Retrieval#303",
        "3#3D object reconstructions#337",
        "4#Theoretical introduction#338",
        "4#Algorithms for tomographic reconstruction#352",
        "3#Deep learning approach#413",
        "4#Quick overview of deep learning#416",
        "4#Neural Radiance Fields (NeRF)#423",
        "4#PixelNeRF - NeRF from one or few images#491",
        "4#ONIX#516",
        "2#Materials and Methods#545",
        "3#Flat-field correction#546",
        "3#Tomographic reconstructions#584",
        "2#Results and Discussion#603",
        "3#Flat-field normalisation#608",
        "4#Comparison of FFC methods#618",
        "3#Comparison of reconstruction algorithms#629",
        "2#reformulate#648",
        "2#check last sentence#658",
        "3#Training attempts#686",
        "2#CHECK GRAMM#708",
        "2#Conclusion#712",
        "2#Resumé#734"
    ],
    "usercommands": [
        [
            "\\codestyle",
            "\\codestyle"
        ]
    ]
}
